elicit/__init__.py
elicit/all.py
elicit/autodebug.py
elicit/colors.py
elicit/commands.py
elicit/completer.py
elicit/console.py
elicit/controller.py
elicit/debugger.py
elicit/docopt.py
elicit/env.py
elicit/exceptions.py
elicit/fsm.py
elicit/parser.py
elicit/python.py
elicit/simpleui.py
elicit/themes.py
elicit/ui.py
elicit/util.py
elicit/widgets.py
elicit/__pycache__/__init__.cpython-310.opt-1.pyc
elicit/__pycache__/all.cpython-310.opt-1.pyc
elicit/__pycache__/autodebug.cpython-310.opt-1.pyc
elicit/__pycache__/colors.cpython-310.opt-1.pyc
elicit/__pycache__/commands.cpython-310.opt-1.pyc
elicit/__pycache__/completer.cpython-310.opt-1.pyc
elicit/__pycache__/console.cpython-310.opt-1.pyc
elicit/__pycache__/controller.cpython-310.opt-1.pyc
elicit/__pycache__/debugger.cpython-310.opt-1.pyc
elicit/__pycache__/docopt.cpython-310.opt-1.pyc
elicit/__pycache__/env.cpython-310.opt-1.pyc
elicit/__pycache__/exceptions.cpython-310.opt-1.pyc
elicit/__pycache__/fsm.cpython-310.opt-1.pyc
elicit/__pycache__/parser.cpython-310.opt-1.pyc
elicit/__pycache__/python.cpython-310.opt-1.pyc
elicit/__pycache__/simpleui.cpython-310.opt-1.pyc
elicit/__pycache__/themes.cpython-310.opt-1.pyc
elicit/__pycache__/ui.cpython-310.opt-1.pyc
elicit/__pycache__/util.cpython-310.opt-1.pyc
elicit/__pycache__/widgets.cpython-310.opt-1.pyc
elicit/present/__init__.py
elicit/present/presentation.py
elicit/present/__pycache__/__init__.cpython-310.opt-1.pyc
elicit/present/__pycache__/presentation.cpython-310.opt-1.pyc
elicit/present/data/separator-1.png
elicit-1.7.2.data/scripts/eldb
elicit-1.7.2.dist-info/LICENSE.txt
elicit-1.7.2.dist-info/METADATA
elicit-1.7.2.dist-info/WHEEL
elicit-1.7.2.dist-info/top_level.txt
elicit-1.7.2.dist-info/RECORD
