Metadata-Version: 2.1
Name: elicit
Version: 1.7.2
Summary: Library for making command-style user interfaces.
Home-page: https://github.com/kdart/elicit
Author: Keith Dart
Author-email: keith@dartworks.biz
License: Apache 2.0
Platform: UNKNOWN
Classifier: Development Status :: 5 - Production/Stable
Classifier: Environment :: Console
Classifier: Intended Audience :: Developers
Classifier: License :: OSI Approved :: Apache Software License
Classifier: Operating System :: POSIX
Classifier: Programming Language :: Python :: 3 :: Only
Classifier: Topic :: Software Development :: Libraries :: Python Modules
Classifier: Topic :: Software Development :: Debuggers
License-File: LICENSE.txt
